intersphinx_registry/__init__.py
intersphinx_registry/__main__.py
intersphinx_registry/_info.py
intersphinx_registry/cli.py
intersphinx_registry/lookup.py
intersphinx_registry/py.typed
intersphinx_registry/registry.json
intersphinx_registry/rev_search.py
intersphinx_registry/reverse_lookup.py
intersphinx_registry/utils.py
intersphinx_registry-0.2601.5.dist-info/entry_points.txt
intersphinx_registry-0.2601.5.dist-info/licenses/LICENSE
intersphinx_registry-0.2601.5.dist-info/WHEEL
intersphinx_registry-0.2601.5.dist-info/METADATA
intersphinx_registry-0.2601.5.dist-info/RECORD
