Metadata-Version: 2.4
Name: intersphinx_registry
Version: 0.2601.5
Summary: This package provides convenient utilities and data to write a sphinx config file.
Author-email: M Bussonnier <bussonniermatthias@gmail.com>
Classifier: License :: OSI Approved :: MIT License
License-File: LICENSE
Requires-Dist: intersphinx_registry[lookup] ; extra == "cli"
Requires-Dist: sphinx>=8 ; extra == "lookup"
Requires-Dist: requests ; extra == "lookup"
Requires-Dist: requests-cache ; extra == "lookup"
Requires-Dist: platformdirs ; extra == "lookup"
Requires-Dist: pytest>=7.0 ; extra == "tests"
Requires-Dist: pytest-xdist ; extra == "tests"
Requires-Dist: mypy ; extra == "tests"
Requires-Dist: types-requests ; extra == "tests"
Requires-Dist: intersphinx_registry[cli] ; extra == "tests"
Project-URL: Home, https://github.com/Quansight-labs/intersphinx_registry
Provides-Extra: cli
Provides-Extra: lookup
Provides-Extra: tests
